openplayground.py
openplayground_api-0.1.1.dist-info/LICENSE
openplayground_api-0.1.1.dist-info/METADATA
openplayground_api-0.1.1.dist-info/WHEEL
openplayground_api-0.1.1.dist-info/top_level.txt
openplayground_api-0.1.1.dist-info/RECORD
