Metadata-Version: 2.1
Name: openplayground-api
Version: 0.1.1
Summary: A reverse engineered API wrapper for OpenPlayground (nat.dev)
Home-page: https://github.com/ading2210/openplayground-api
Author: ading2210
License: GPLv3
Classifier: Programming Language :: Python :: 3
Classifier: License :: OSI Approved :: GNU General Public License (GPL)
Classifier: Operating System :: OS Independent
Requires-Python: >=3.6
License-File: LICENSE
Requires-Dist: pycryptodome
